gcs_client/.base.py.swp
gcs_client/.swp
gcs_client/__init__.py
gcs_client/base.py
gcs_client/bucket.py
gcs_client/common.py
gcs_client/constants.py
gcs_client/credentials.py
gcs_client/errors.py
gcs_client/gcs_object.py
gcs_client/prefix.py
gcs_client/project.py
gcs_client-0.2.2.dist-info/DESCRIPTION.rst
gcs_client-0.2.2.dist-info/METADATA
gcs_client-0.2.2.dist-info/RECORD
gcs_client-0.2.2.dist-info/WHEEL
gcs_client-0.2.2.dist-info/metadata.json
gcs_client-0.2.2.dist-info/top_level.txt
