Metadata-Version: 1.1
Name: gcs-client
Version: 0.2.2
Summary: Google Cloud Storage Python client
Home-page: https://github.com/Akrog/gcs-client
Author: Gorka Eguileor
Author-email: gorka@eguileor.com
License: Apache License 2.0
Keywords: gcs-client
Platform: UNKNOWN
Classifier: Development Status :: 2 - Pre-Alpha
Classifier: Intended Audience :: Developers
Classifier: License :: OSI Approved :: Apache Software License
Classifier: Natural Language :: English
Classifier: Programming Language :: Python :: 2
Classifier: Programming Language :: Python :: 2.7
Classifier: Programming Language :: Python :: 3
Classifier: Programming Language :: Python :: 3.3
Classifier: Programming Language :: Python :: 3.4
